[{
  "_id": {
    "$oid": "67ab6ea9b7af012d9ada21c5"
  },
  "nombre": "SilverSurfer",
  "email": "carlosdepet@gwwail.com",
  "password": "1",
  "telefono": "628192253",
  "direccion": "C.Mejico N 1",
  "tipo": "cliente",
  "historial": "",
  "servicios": "",
  "id": "1739183486723"
},
{
  "_id": {
    "$oid": "67ac65990054ac04e46050e4"
  },
  "nombre": "HOla",
  "email": "juan@gmail.com",
  "password": "1",
  "telefono": "12312312",
  "direccion": "12313132"
},
{
  "_id": {
    "$oid": "67ac72bed9875a3ac6bb1d6b"
  },
  "nombre": "JuanCarlosPetr",
  "email": "carlosdepet@gmail.com",
  "password": "1",
  "telefono": "628192253",
  "direccion": "C.Mejico N 1",
  "favoritos": [
    {
      "$oid": "67aef9e003090d9cf40e61e4"
    }
  ]
},
{
  "_id": {
    "$oid": "67ac90dd451e0c959b3fa1d9"
  },
  "nombre": "CarlosPresiDiiario",
  "email": "carlosdepet@gmaaail.com",
  "password": "1",
  "telefono": "628192253",
  "direccion": "C.Mejico N 1",
  "favoritos": [
    {
      "$oid": "67aca81daf4127da26264dcc"
    },
    "67adf5bd57c22acea14a6cda"
  ]
},
{
  "_id": {
    "$oid": "67aef92003090d9cf40e61e3"
  },
  "nombre": "Juan El panadero",
  "email": "JuanPanadero@gmail.com",
  "password": "1",
  "telefono": "62222222233",
  "direccion": "Calle de los Buitres 38",
  "favoritos": [
    {
      "$oid": "67ab6961b7af012d9ada21a4"
    },
    {
      "$oid": "67ab6961b7af012d9ada21a3"
    }
  ]
}]